squat/__init__.py
squat/classifier.py
squat/cli.py
squat/Classifier/ClassifierUtil.py
squat/Classifier/__init__.py
squat/Classifier/classifier_cli.py
squat/Classifier/classifier_model.py
squat/Classifier/train.csv
squat/Classifier/out/meta.json
squat/Classifier/out/tokenizer
squat/Classifier/out/textcat/cfg
squat/Classifier/out/textcat/model
squat/Classifier/out/vocab/key2row
squat/Classifier/out/vocab/lexemes.bin
squat/Classifier/out/vocab/strings.json
squat/Classifier/out/vocab/vectors
squat-1.0.3.dist-info/LICENSE.txt
squat-1.0.3.dist-info/METADATA
squat-1.0.3.dist-info/WHEEL
squat-1.0.3.dist-info/dependency_links.txt
squat-1.0.3.dist-info/entry_points.txt
squat-1.0.3.dist-info/top_level.txt
squat-1.0.3.dist-info/RECORD
