Metadata-Version: 2.1
Name: squat
Version: 1.0.3
Summary: SQUAT
Home-page: https://github.com/binayr/SQUAT.git
Author: Binay Kumar Ray
Author-email: binayray2009@gmail.com
License: UNKNOWN
Platform: UNKNOWN
Classifier: Programming Language :: Python :: 3
Classifier: License :: OSI Approved :: MIT License
Classifier: Operating System :: OS Independent
Requires-Dist: spacy
Requires-Dist: pandas
Requires-Dist: jupyter
Requires-Dist: arghandler
